prefixed_aiostatsd/__init__.py
prefixed_aiostatsd-1.2.dist-info/LICENSE
prefixed_aiostatsd-1.2.dist-info/METADATA
prefixed_aiostatsd-1.2.dist-info/WHEEL
prefixed_aiostatsd-1.2.dist-info/top_level.txt
prefixed_aiostatsd-1.2.dist-info/RECORD
